./.gitignore
./PKG-INFO
./README.md
./__init__.py
./__main__.py
./pyproject.toml
./server.py
./tools/csv_tools.py
./tools/parquet_tools.py
./utils/file_reader.py
ada_agentic-0.1.0.dist-info/METADATA
ada_agentic-0.1.0.dist-info/WHEEL
ada_agentic-0.1.0.dist-info/entry_points.txt
ada_agentic-0.1.0.dist-info/RECORD
