Metadata-Version: 2.4
Name: ada-agentic
Version: 0.1.0
Summary: Ayala Agentic AI - MCP Server Implementation
Project-URL: Documentation, https://github.com/ac-analytics/ada/tree/main/src/agentic#readme
Project-URL: Source, https://github.com/ac-analytics/ada
Project-URL: Tracker, https://github.com/ac-analytics/ada/issues
Author-email: AC Analytics <analytics@ayala.com>
Classifier: Development Status :: 3 - Alpha
Classifier: Intended Audience :: Developers
Classifier: License :: OSI Approved :: MIT License
Classifier: Programming Language :: Python :: 3 :: Only
Classifier: Programming Language :: Python :: 3.10
Classifier: Programming Language :: Python :: 3.11
Classifier: Programming Language :: Python :: 3.12
Requires-Python: >=3.10
Requires-Dist: mcp[cli]==1.3.0
